geo_nx/__init__.py
geo_nx/algorithms.py
geo_nx/convert.py
geo_nx/geograph.py
geo_nx/utils.py
geo_nx-0.2.0.dist-info/METADATA
geo_nx-0.2.0.dist-info/WHEEL
geo_nx-0.2.0.dist-info/top_level.txt
geo_nx-0.2.0.dist-info/RECORD
