Metadata-Version: 2.1
Name: geo_nx
Version: 0.2.0
Summary: Geo-NX : Geospatial Network Analysis
Home-page: https://github.com/loco-labs/geo_nx/blob/main/README.md
Author: Philippe Thomy
Author-email: philippe@loco-labs.io
Keywords: network,geographic,geospatial,open data
Classifier: Development Status :: 3 - Alpha
Classifier: Intended Audience :: Developers
Classifier: Topic :: Software Development :: Build Tools
Classifier: License :: OSI Approved :: MIT License
Classifier: Programming Language :: Python :: 3
Requires-Python: >=3.11, <4
Requires-Dist: shapely
Requires-Dist: geopandas
